// class version 52.0 (52)
// access flags 0x21
public class rhythm/analysis/model/suffixTree/SuffixTree {

  // compiled from: SuffixTree.java
  // access flags 0x0
  INNERCLASS rhythm/analysis/model/suffixTree/SuffixTree$1  

  // access flags 0x2
  private Lrhythm/analysis/model/suffixTree/Node; root

  // access flags 0x2
  private Ljava/lang/String; string

  // access flags 0x2
  private I numPulses

  // access flags 0x2
  private I minSubStrLength

  // access flags 0x2
  private Lrhythm/analysis/control/RhythmController; controller

  // access flags 0x1
  public <init>()V
   L0
    LINENUMBER 46 L0
    ALOAD 0
    INVOKESPECIAL java/lang/Object.<init> ()V
   L1
    LINENUMBER 47 L1
    ALOAD 0
    LDC ""
    PUTFIELD rhythm/analysis/model/suffixTree/SuffixTree.string : Ljava/lang/String;
   L2
    LINENUMBER 48 L2
    ALOAD 0
    NEW rhythm/analysis/model/suffixTree/NodeRoot
    DUP
    INVOKESPECIAL rhythm/analysis/model/suffixTree/NodeRoot.<init> ()V
    PUTFIELD rhythm/analysis/model/suffixTree/SuffixTree.root : Lrhythm/analysis/model/suffixTree/Node;
   L3
    LINENUMBER 49 L3
    ALOAD 0
    ICONST_1
    PUTFIELD rhythm/analysis/model/suffixTree/SuffixTree.minSubStrLength : I
   L4
    LINENUMBER 50 L4
    ALOAD 0
    BIPUSH 8
    PUTFIELD rhythm/analysis/model/suffixTree/SuffixTree.numPulses : I
   L5
    LINENUMBER 51 L5
    RETURN
   L6
    LOCALVARIABLE this Lrhythm/analysis/model/suffixTree/SuffixTree; L0 L6 0
    MAXSTACK = 3
    MAXLOCALS = 1

  // access flags 0x1
  public <init>(Lrhythm/analysis/control/RhythmController;)V
   L0
    LINENUMBER 55 L0
    ALOAD 0
    INVOKESPECIAL rhythm/analysis/model/suffixTree/SuffixTree.<init> ()V
   L1
    LINENUMBER 56 L1
    ALOAD 0
    ALOAD 1
    PUTFIELD rhythm/analysis/model/suffixTree/SuffixTree.controller : Lrhythm/analysis/control/RhythmController;
   L2
    LINENUMBER 57 L2
    RETURN
   L3
    LOCALVARIABLE this Lrhythm/analysis/model/suffixTree/SuffixTree; L0 L3 0
    LOCALVARIABLE controller Lrhythm/analysis/control/RhythmController; L0 L3 1
    MAXSTACK = 2
    MAXLOCALS = 2

  // access flags 0x1
  public reset()V
   L0
    LINENUMBER 61 L0
    ALOAD 0
    LDC ""
    PUTFIELD rhythm/analysis/model/suffixTree/SuffixTree.string : Ljava/lang/String;
   L1
    LINENUMBER 62 L1
    ALOAD 0
    ACONST_NULL
    PUTFIELD rhythm/analysis/model/suffixTree/SuffixTree.root : Lrhythm/analysis/model/suffixTree/Node;
   L2
    LINENUMBER 63 L2
    ALOAD 0
    NEW rhythm/analysis/model/suffixTree/NodeRoot
    DUP
    INVOKESPECIAL rhythm/analysis/model/suffixTree/NodeRoot.<init> ()V
    PUTFIELD rhythm/analysis/model/suffixTree/SuffixTree.root : Lrhythm/analysis/model/suffixTree/Node;
   L3
    LINENUMBER 64 L3
    RETURN
   L4
    LOCALVARIABLE this Lrhythm/analysis/model/suffixTree/SuffixTree; L0 L4 0
    MAXSTACK = 3
    MAXLOCALS = 1