// class version 52.0 (52)
// access flags 0x21
public class JoolsTest {

  // compiled from: JoolsTest.java

  // access flags 0x0
  Ljava/lang/String; string

  // access flags 0x0
  Ljava/lang/String; string2

  // access flags 0x1
  public <init>()V
   L0
    LINENUMBER 6 L0
    ALOAD 0
    INVOKESPECIAL java/lang/Object.<init> ()V
   L1
    LINENUMBER 8 L1
    ALOAD 0
    LDC "ab"
    PUTFIELD JoolsTest.string : Ljava/lang/String;
   L2
    LINENUMBER 9 L2
    ALOAD 0
    LDC "aba"
    PUTFIELD JoolsTest.string2 : Ljava/lang/String;
   L3
    LINENUMBER 6 L3
    RETURN
   L4
    LOCALVARIABLE this LJoolsTest; L0 L4 0
    MAXSTACK = 2
    MAXLOCALS = 1

  // access flags 0x9
  public static main([Ljava/lang/String;)V
   L0
    LINENUMBER 13 L0
    NEW JoolsTest
    DUP
    INVOKESPECIAL JoolsTest.<init> ()V
    ASTORE 1
   L1
    LINENUMBER 15 L1
    GETSTATIC java/lang/System.out : Ljava/io/PrintStream;
    ALOAD 1
    LDC "a"
    INVOKEVIRTUAL JoolsTest.getCommonPrefix (Ljava/lang/String;)Ljava/lang/String;
    INVOKEVIRTUAL java/io/PrintStream.println (Ljava/lang/String;)V
   L2
    LINENUMBER 16 L2
    RETURN
   L3
    LOCALVARIABLE args [Ljava/lang/String; L0 L3 0
    LOCALVARIABLE j LJoolsTest; L1 L3 1
    MAXSTACK = 3
    MAXLOCALS = 2

  // access flags 0x1
  public removeNodeFromArg(Ljava/lang/String;)Ljava/lang/String;
   L0
    LINENUMBER 20 L0
    ALOAD 1
    ALOAD 0
    GETFIELD JoolsTest.string : Ljava/lang/String;
    INVOKEVIRTUAL java/lang/String.length ()I
    INVOKEVIRTUAL java/lang/String.substring (I)Ljava/lang/String;
    ARETURN
   L1
    LOCALVARIABLE this LJoolsTest; L0 L1 0
    LOCALVARIABLE string Ljava/lang/String; L0 L1 1
    MAXSTACK = 2
    MAXLOCALS = 2

  // access flags 0x1
  public removeArgFromNode(Ljava/lang/String;)Ljava/lang/String;
   L0
    LINENUMBER 24 L0
    ALOAD 0
    GETFIELD JoolsTest.string2 : Ljava/lang/String;
    ALOAD 1
    INVOKEVIRTUAL java/lang/String.length ()I
    INVOKEVIRTUAL java/lang/String.substring (I)Ljava/lang/String;
    ARETURN
   L1
    LOCALVARIABLE this LJoolsTest; L0 L1 0
    LOCALVARIABLE string Ljava/lang/String; L0 L1 1
    MAXSTACK = 2
    MAXLOCALS = 2

  // access flags 0x1
  public getCommonPrefix(Ljava/lang/String;)Ljava/lang/String;
   L0
    LINENUMBER 29 L0
    ALOAD 0
    GETFIELD JoolsTest.string : Ljava/lang/String;
    INVOKEVIRTUAL java/lang/String.length ()I
    ALOAD 1
    INVOKEVIRTUAL java/lang/String.length ()I
    IF_ICMPLE L1
   L2
    LINENUMBER 30 L2
    ALOAD 0
    GETFIELD JoolsTest.string : Ljava/lang/String;
    ICONST_0
    ALOAD 1
    INVOKEVIRTUAL java/lang/String.length ()I
    INVOKEVIRTUAL java/lang/String.substring (II)Ljava/lang/String;
    ARETURN
   L1
    LINENUMBER 32 L1
   FRAME SAME
    ALOAD 1
    ICONST_0
    ALOAD 0
    GETFIELD JoolsTest.string : Ljava/lang/String;
    INVOKEVIRTUAL java/lang/String.length ()I
    INVOKEVIRTUAL java/lang/String.substring (II)Ljava/lang/String;
    ARETURN
   L3
    LOCALVARIABLE this LJoolsTest; L0 L3 0
    LOCALVARIABLE string Ljava/lang/String; L0 L3 1
    MAXSTACK = 3
    MAXLOCALS = 2

  // access flags 0x1
  public setSubString(I)V
   L0
    LINENUMBER 38 L0
    ALOAD 0
    ALOAD 0
    GETFIELD JoolsTest.string : Ljava/lang/String;
    ILOAD 1
    INVOKEVIRTUAL java/lang/String.substring (I)Ljava/lang/String;
    PUTFIELD JoolsTest.string : Ljava/lang/String;
   L1
    LINENUMBER 39 L1
    RETURN
   L2
    LOCALVARIABLE this LJoolsTest; L0 L2 0
    LOCALVARIABLE start I L0 L2 1
    MAXSTACK = 3
    MAXLOCALS = 2
}
